<?xml version="1.0" encoding="UTF-8"?>
<GridConfig>
	<id>GRIDS.PARENT_CONTAINERS_TAB</id>
	<name>GRIDS.PARENT_CONTAINERS_TAB</name>
	<size>
		<height>400</height>
		<width>600</width>
	</size>	
	<pagination>		
		<loadingSize>100</loadingSize>
	</pagination>
	<header>
		<show>true</show>
		<title>Custom Grid Component</title>
		<align>left</align>
	</header>
	<views>
		<show>false</show>
		<title>Views</title>
		<defaultViewText>Default</defaultViewText>		
	</views>
	<search>
		<show>true</show>
		<title>Search</title>
		<textWidth>300</textWidth>		
	</search>      
    <hideShowColumns>
		<show>true</show>
		<title>Show/ Hide Columns</title>		
    </hideShowColumns>  
	<lookup>
		<show>false</show>
		<title>Quick Look</title>
		<textWidth>200</textWidth>		
	</lookup>      
	<recordCount>
		<show>true</show>
		<title>Containers :</title>		
	</recordCount>
    <tools>
    	<title>Tools</title>
		<show>false</show>		
    </tools>
    <contextMenu>
    	<menus>
    		<menu>
    			<title>Add Task</title>
    			<icon>images/add.png</icon>
    			<function>doAdd</function>
    			<type>grid</type>
    		</menu>
    		<menu>
    			<title>Edit Task</title>
    			<icon>images/edit.png</icon>
    			<function>doEdit</function>
    			<type>row</type>
    		</menu>
    		<menu>
    			<title>Delete Task</title>
    			<icon>images/delete.png</icon>
    			<function>doDelete</function>
    			<type>row</type>
    		</menu>
    	</menus>
    </contextMenu>
    <functions>
    	<rowClickCallback>callSingleClick</rowClickCallback>
    	<rowDoubleClickCallback>callDoubleClick</rowDoubleClickCallback>
    </functions>

	<columns>
	    <column>
			<title>Container Code</title>
			<dataField>containerVrsn.containerVrsnCode</dataField>
			<dataType>String</dataType>
			<width>140</width>
			<visible>true</visible>
			<hide>false</hide>
			<sort>true</sort>
			<filter>true</filter>
			<search>true</search>
			<resize>true</resize>
			<dragable>true</dragable>
		</column>			
	    <column>
			<title>Top Container</title>
			<dataField>topContainerVrsn.containerVrsnCode</dataField>
			<dataType>String</dataType>
			<width>140</width>
			<visible>true</visible>
			<hide>true</hide>
			<sort>true</sort>
			<filter>true</filter>
			<search>true</search>
			<resize>true</resize>
			<dragable>true</dragable>
		</column>			
		<column>
			<title>Top Container Vrsn#</title>
			<dataField>topContainerVrsn.versionNo</dataField>
			<dataType>Number</dataType>
			<width>170</width>
			<visible>true</visible>
			<hide>true</hide>
			<sort>true</sort>
			<filter>true</filter>
			<search>true</search>
			<resize>true</resize>
			<dragable>true</dragable>
		</column>
		<column>
			<title>Top Container Status</title>
			<dataField>topContainerVrsn.containerStatus.presentWorkflowStatusType.workflowStatusTypeCode</dataField>
			<dataType>String</dataType>
			<width>170</width>
			<visible>true</visible>
			<hide>true</hide>
			<sort>true</sort>
			<filter>true</filter>
			<search>true</search>
			<resize>true</resize>
			<dragable>true</dragable>
		</column>		
	    <column>
			<title>Parent Container</title>
			<dataField>parentContainerVrsn.containerVrsnCode</dataField>
			<dataType>String</dataType>
			<width>140</width>
			<visible>true</visible>
			<hide>true</hide>
			<sort>true</sort>
			<filter>true</filter>
			<search>true</search>
			<resize>true</resize>
			<dragable>true</dragable>
		</column>			
		<column>
			<title>Parent Container Vrsn#</title>
			<dataField>parentContainerVrsn.versionNo</dataField>
			<dataType>Number</dataType>
			<width>180</width>
			<visible>true</visible>
			<hide>true</hide>
			<sort>true</sort>
			<filter>true</filter>
			<search>true</search>
			<resize>true</resize>
			<dragable>true</dragable>
		</column>
		<column>
			<title>Parent Container Status</title>
			<dataField>parentContainerVrsn.containerStatus.presentWorkflowStatusType.workflowStatusTypeCode</dataField>
			<dataType>String</dataType>
			<width>180</width>
			<visible>true</visible>
			<hide>true</hide>
			<sort>true</sort>
			<filter>true</filter>
			<search>true</search>
			<resize>true</resize>
			<dragable>true</dragable>
		</column>	
		<column>
			<title>Level#</title>
			<dataField>levelNo</dataField>
			<dataType>Number</dataType>
			<width>90</width>
			<visible>true</visible>
			<hide>true</hide>
			<sort>true</sort>
			<filter>true</filter>
			<search>true</search>
			<resize>true</resize>
			<dragable>true</dragable>
		</column>		
	</columns>
</GridConfig>
